roads_cba_py/__init__.py
roads_cba_py/cba.py
roads_cba_py/cba_result.py
roads_cba_py/config.py
roads_cba_py/defaults.py
roads_cba_py/section.py
roads_cba_py/utils.py
roads_cba_py-0.1.2.dist-info/METADATA
roads_cba_py-0.1.2.dist-info/WHEEL
roads_cba_py-0.1.2.dist-info/top_level.txt
roads_cba_py-0.1.2.dist-info/RECORD
