Metadata-Version: 2.1
Name: roads-cba-py
Version: 0.1.2
Summary: A pure python implementation of a CBA analysis for road maintenance prioritisation
Home-page: https://github.com/vnopenroads/roads-cba-py
Author: Jamie Cook
Author-email: jimi.cook@gmail.com
License: UNKNOWN
Platform: UNKNOWN
Classifier: Programming Language :: Python :: 3
Classifier: License :: OSI Approved :: MIT License
Classifier: Operating System :: OS Independent
Requires-Python: >=3.6
Requires-Dist: numpy
Requires-Dist: numpy-financial
Requires-Dist: pandas
Requires-Dist: schematics
Requires-Dist: intervaltree
